chopify/__init__.py
chopify-1.1.0.dist-info/licenses/LICENSE.md
chopify-1.1.0.dist-info/METADATA
chopify-1.1.0.dist-info/WHEEL
chopify-1.1.0.dist-info/top_level.txt
chopify-1.1.0.dist-info/RECORD
